sqlalchemy_debug/__init__.py
sqlalchemy_debug/main.py
sqlalchemy_debug-0.3.4.dist-info/METADATA
sqlalchemy_debug-0.3.4.dist-info/WHEEL
sqlalchemy_debug-0.3.4.dist-info/top_level.txt
sqlalchemy_debug-0.3.4.dist-info/RECORD
