Metadata-Version: 2.1
Name: sqlalchemy-debug
Version: 0.3.4
Summary: a tool for debug sqlalchemy model
Home-page: UNKNOWN
Author: UNKNOWN
Author-email: UNKNOWN
License: UNKNOWN
Keywords: sqlalchemy
Platform: any
Requires-Dist: SQLAlchemy (>=1.0)
